ntnx_security_py_client/__init__.py
ntnx_security_py_client/api_client.py
ntnx_security_py_client/api_response.py
ntnx_security_py_client/configuration.py
ntnx_security_py_client/custom_retry.py
ntnx_security_py_client/rest.py
ntnx_security_py_client/api/__init__.py
ntnx_security_py_client/api/approval_policies_api.py
ntnx_security_py_client/api/credentials_api.py
ntnx_security_py_client/api/key_management_servers_api.py
ntnx_security_py_client/api/security_summaries_api.py
ntnx_security_py_client/api/sti_gs_api.py
ntnx_security_py_client/api/vulnerabilities_api.py
ntnx_security_py_client/models/__init__.py
ntnx_security_py_client/models/OneOfcommon/__init__.py
ntnx_security_py_client/models/OneOfcommon/v1/__init__.py
ntnx_security_py_client/models/OneOfcommon/v1/config/KVPairvalue.py
ntnx_security_py_client/models/OneOfcommon/v1/config/__init__.py
ntnx_security_py_client/models/OneOfsecurity/__init__.py
ntnx_security_py_client/models/OneOfsecurity/v4/__init__.py
ntnx_security_py_client/models/OneOfsecurity/v4/config/CreateCredentialApiResponsedata.py
ntnx_security_py_client/models/OneOfsecurity/v4/config/CreateKeyManagementServerApiResponsedata.py
ntnx_security_py_client/models/OneOfsecurity/v4/config/Credentialcredential_details.py
ntnx_security_py_client/models/OneOfsecurity/v4/config/DeleteCredentialApiResponsedata.py
ntnx_security_py_client/models/OneOfsecurity/v4/config/DeleteKeyManagementServerApiResponsedata.py
ntnx_security_py_client/models/OneOfsecurity/v4/config/GetCredentialApiResponsedata.py
ntnx_security_py_client/models/OneOfsecurity/v4/config/GetKeyManagementServerApiResponsedata.py
ntnx_security_py_client/models/OneOfsecurity/v4/config/KeyManagementServeraccess_information.py
ntnx_security_py_client/models/OneOfsecurity/v4/config/ListCredentialsApiResponsedata.py
ntnx_security_py_client/models/OneOfsecurity/v4/config/ListKeyManagementServersApiResponsedata.py
ntnx_security_py_client/models/OneOfsecurity/v4/config/UpdateCredentialApiResponsedata.py
ntnx_security_py_client-4.1.1.dist-info/LICENSE.txt
ntnx_security_py_client-4.1.1.dist-info/METADATA
ntnx_security_py_client-4.1.1.dist-info/WHEEL
ntnx_security_py_client-4.1.1.dist-info/top_level.txt
ntnx_security_py_client-4.1.1.dist-info/RECORD
